rnavirhost/__init__.py
rnavirhost/rnavirhost.py
rnavirhost/model/order_assign.csv
rnavirhost/model/order_pred.csv
rnavirhost/model/Amarillovirales/L1_onehot2taxa.pkl
rnavirhost/model/Amarillovirales/L2_onehot2taxa.pkl
rnavirhost/model/Amarillovirales/blast_db.ndb
rnavirhost/model/Amarillovirales/blast_db.nhr
rnavirhost/model/Amarillovirales/blast_db.nin
rnavirhost/model/Amarillovirales/blast_db.not
rnavirhost/model/Amarillovirales/blast_db.nsq
rnavirhost/model/Amarillovirales/blast_db.ntf
rnavirhost/model/Amarillovirales/blast_db.nto
rnavirhost/model/Amarillovirales/cutoff.pkl
rnavirhost/model/Amarillovirales/data_label.csv
rnavirhost/model/Amarillovirales/host_info.pkl
rnavirhost/model/Amarillovirales/xgb_sub_bl_L1.model
rnavirhost/model/Amarillovirales/xgb_sub_bl_L2.model
rnavirhost/model/Articulavirales/L1_onehot2taxa.pkl
rnavirhost/model/Articulavirales/L2_onehot2taxa.pkl
rnavirhost/model/Articulavirales/blast_db.ndb
rnavirhost/model/Articulavirales/blast_db.nhr
rnavirhost/model/Articulavirales/blast_db.nin
rnavirhost/model/Articulavirales/blast_db.not
rnavirhost/model/Articulavirales/blast_db.nsq
rnavirhost/model/Articulavirales/blast_db.ntf
rnavirhost/model/Articulavirales/blast_db.nto
rnavirhost/model/Articulavirales/cutoff.pkl
rnavirhost/model/Articulavirales/data_label.csv
rnavirhost/model/Articulavirales/host_info.pkl
rnavirhost/model/Articulavirales/xgb_sub_bl_L1.model
rnavirhost/model/Articulavirales/xgb_sub_bl_L2.model
rnavirhost/model/Blubervirales/L1_onehot2taxa.pkl
rnavirhost/model/Blubervirales/L2_onehot2taxa.pkl
rnavirhost/model/Blubervirales/blast_db.ndb
rnavirhost/model/Blubervirales/blast_db.nhr
rnavirhost/model/Blubervirales/blast_db.nin
rnavirhost/model/Blubervirales/blast_db.not
rnavirhost/model/Blubervirales/blast_db.nsq
rnavirhost/model/Blubervirales/blast_db.ntf
rnavirhost/model/Blubervirales/blast_db.nto
rnavirhost/model/Blubervirales/cutoff.pkl
rnavirhost/model/Blubervirales/data_label.csv
rnavirhost/model/Blubervirales/host_info.pkl
rnavirhost-1.0.5.dist-info/LICENSE.txt
rnavirhost-1.0.5.dist-info/METADATA
rnavirhost-1.0.5.dist-info/WHEEL
rnavirhost-1.0.5.dist-info/entry_points.txt
rnavirhost-1.0.5.dist-info/top_level.txt
rnavirhost-1.0.5.dist-info/RECORD
